Workbook

Sheet BudgetBuddy Test Cases
A1: BudgetBuddy - Functional Test Cases
A2: Module | B2: Test Case No | C2: Test Case Scenario | D2: Test Input / Preconditions | E2: Expected Output | F2: Actual Output | G2: Result (Pass/Fail)
A3: Registration & Verification | B3: REG1 | C3: Successful registration | D3: Valid full name, unique email, strong password | E3: Account is created and a verification code is sent to the registered email. | F3: Not Executed | G3: Not Executed
B4: REG2 | C4: Reject duplicate email | D4: Email already registered | E4: Registration is rejected with a clear duplicate-email message. | F4: Not Executed | G4: Not Executed
B5: REG3 | C5: Reject invalid email | D5: Email: user@invalid | E5: Email-format validation is shown and no account is created. | F5: Not Executed | G5: Not Executed
B6: REG4 | C6: Reject weak password | D6: Password missing required length/complexity | E6: Password validation is shown and no account is created. | F6: Not Executed | G6: Not Executed
B7: REG5 | C7: Reject missing required fields | D7: Blank name, email, or password | E7: Required-field validation is displayed. | F7: Not Executed | G7: Not Executed
B8: REG6 | C8: Verify email with valid code | D8: Registered email and active verification code | E8: Account becomes verified and can log in. | F8: Not Executed | G8: Not Executed
B9: REG7 | C9: Reject invalid verification code | D9: Registered email and incorrect code | E9: Verification fails without activating the account. | F9: Not Executed | G9: Not Executed
B10: REG8 | C10: Reject expired verification code | D10: Registered email and expired code | E10: User is told the code expired and account remains unverified. | F10: Not Executed | G10: Not Executed
A11: Login & Session | B11: LOG1 | C11: Successful Free User login | D11: Verified Free User credentials | E11: Login succeeds, JWT is stored, and Overview opens. | F11: Not Executed | G11: Not Executed
B12: LOG2 | C12: Successful Premium User login | D12: Verified Premium User credentials | E12: Login succeeds and Overview opens with Premium access available. | F12: Not Executed | G12: Not Executed
B13: LOG3 | C13: Successful Admin login | D13: Verified Admin credentials | E13: Login succeeds and Overview opens; Admin navigation is available. | F13: Not Executed | G13: Not Executed
B14: LOG4 | C14: Reject incorrect password | D14: Valid email and incorrect password | E14: Login is rejected with an invalid-credentials message. | F14: Not Executed | G14: Not Executed
B15: LOG5 | C15: Reject unknown email | D15: Unregistered email and any password | E15: Login is rejected without revealing sensitive account details. | F15: Not Executed | G15: Not Executed
B16: LOG6 | C16: Reject unverified account | D16: Correct credentials for unverified account | E16: Access is denied until email verification is completed. | F16: Not Executed | G16: Not Executed
B17: LOG7 | C17: Protected route without token | D17: Open /dashboard without JWT | E17: User is redirected to Login. | F17: Not Executed | G17: Not Executed
B18: LOG8 | C18: Expired or invalid token | D18: Call a protected API with invalid/expired JWT | E18: API returns 401 and the client clears the invalid session. | F18: Not Executed | G18: Not Executed
B19: LOG9 | C19: Logout | D19: Click Logout while authenticated | E19: JWT is removed and the user returns to Login. | F19: Not Executed | G19: Not Executed
B20: LOG10 | C20: Deactivated account | D20: Valid credentials for an inactive account | E20: Protected access is rejected with an account-deactivated message. | F20: Not Executed | G20: Not Executed
A21: Overview | B21: OVR1 | C21: Overview loads summary | D21: Authenticated user with financial records | E21: Balance, income, expenses, and savings match that user's data. | F21: Not Executed | G21: Not Executed
B22: OVR2 | C22: Overview empty state | D22: Authenticated user with no records | E22: Zero-value summary and appropriate empty states render without errors. | F22: Not Executed | G22: Not Executed
B23: OVR3 | C23: Month filter updates Overview | D23: Choose a different month | E23: Summary, charts, and transactions update for the selected month. | F23: Not Executed | G23: Not Executed
B24: OVR4 | C24: Recent transactions | D24: User has recent income and expenses | E24: Recent records are shown in correct chronological order and with correct types. | F24: Not Executed | G24: Not Executed
B25: OVR5 | C25: Budget progress | D25: Budget and matching expenses exist | E25: Budget progress reflects the selected user's spending. | F25: Not Executed | G25: Not Executed
B26: OVR6 | C26: Savings-goal progress | D26: Active savings goals exist | E26: Goal progress displays current saved and target amounts. | F26: Not Executed | G26: Not Executed
A27: Income | B27: INC1 | C27: Add income | D27: Valid source, positive amount, description, and account | E27: Income is saved for the authenticated user and totals update. | F27: Not Executed | G27: Not Executed
B28: INC2 | C28: Reject zero or negative income | D28: Amount: 0 or -100 | E28: Validation prevents the income record from being created. | F28: Not Executed | G28: Not Executed
B29: INC3 | C29: List own income only | D29: Two users each have income records | E29: Each user sees only their own income. | F29: Not Executed | G29: Not Executed
B30: INC4 | C30: Edit own income | D30: Change amount/source of owned record | E30: Record updates successfully and summaries recalculate. | F30: Not Executed | G30: Not Executed
B31: INC5 | C31: Prevent editing another user's income | D31: Use another user's income ID | E31: API returns not found/denied and the record is unchanged. | F31: Not Executed | G31: Not Executed
B32: INC6 | C32: Delete own income | D32: Delete an owned income record | E32: Record is removed and totals update. | F32: Not Executed | G32: Not Executed
A33: Expenses | B33: EXP1 | C33: Add expense | D33: Valid category, positive amount, description, and account | E33: Expense is saved for the authenticated user and totals update. | F33: Not Executed | G33: Not Executed
B34: EXP2 | C34: Reject invalid expense amount | D34: Amount: 0 or negative | E34: Validation prevents the expense record from being created. | F34: Not Executed | G34: Not Executed
B35: EXP3 | C35: Require expense description | D35: Valid amount but missing required description | E35: Validation explains that the description is required. | F35: Not Executed | G35: Not Executed
B36: EXP4 | C36: List own expenses only | D36: Two users each have expense records | E36: Each user sees only their own expenses. | F36: Not Executed | G36: Not Executed
B37: EXP5 | C37: Edit own expense | D37: Update owned expense amount/category | E37: Expense updates and affected totals/budgets recalculate. | F37: Not Executed | G37: Not Executed
B38: EXP6 | C38: Prevent editing another user's expense | D38: Use another user's expense ID | E38: API returns not found/denied and data remains unchanged. | F38: Not Executed | G38: Not Executed
B39: EXP7 | C39: Delete own expense | D39: Delete an owned expense | E39: Expense is removed and related totals update. | F39: Not Executed | G39: Not Executed
B40: EXP8 | C40: Budget threshold notification | D40: Expense causes category spending to exceed budget | E40: A single budget alert is generated with the correct message. | F40: Not Executed | G40: Not Executed
A41: Accounts | B41: ACC1 | C41: Add bank account | D41: Valid bank/account details | E41: Account is saved and becomes available in income/expense forms. | F41: Not Executed | G41: Not Executed
B42: ACC2 | C42: List personal accounts | D42: Authenticated user with accounts | E42: Only accounts owned by the current user are displayed. | F42: Not Executed | G42: Not Executed
B43: ACC3 | C43: Edit personal account | D43: Update an owned account | E43: Updated details persist after refresh. | F43: Not Executed | G43: Not Executed
B44: ACC4 | C44: Delete personal account | D44: Delete an owned account | E44: Account is removed without affecting another user's accounts. | F44: Not Executed | G44: Not Executed
B45: ACC5 | C45: Transaction without account | D45: Attempt entry when no account exists | E45: Helpful guidance asks the user to add an account first. | F45: Not Executed | G45: Not Executed
A46: Budgets | B46: BUD1 | C46: Create monthly budget | D46: Category, positive amount, YYYY-MM month | E46: Budget is created for the authenticated user. | F46: Not Executed | G46: Not Executed
B47: BUD2 | C47: Reject duplicate category/month budget | D47: Same user, category, and month | E47: Duplicate budget is rejected with a conflict message. | F47: Not Executed | G47: Not Executed
B48: BUD3 | C48: Budget list by month | D48: Select a month containing budgets | E48: Only the user's budgets for that month are shown. | F48: Not Executed | G48: Not Executed
B49: BUD4 | C49: Budget spending calculation | D49: Budget plus expenses in same category/month | E49: Spent, remaining, and percentage values are correct. | F49: Not Executed | G49: Not Executed
B50: BUD5 | C50: Edit own budget | D50: Update amount on owned budget | E50: Budget and progress values update successfully. | F50: Not Executed | G50: Not Executed
B51: BUD6 | C51: Prevent cross-user budget access | D51: Read/update/delete another user's budget ID | E51: Operations return not found/denied. | F51: Not Executed | G51: Not Executed
B52: BUD7 | C52: Delete own budget | D52: Delete an owned budget | E52: Budget is removed and no other data is changed. | F52: Not Executed | G52: Not Executed
A53: Savings Goals | B53: GOL1 | C53: Create savings goal | D53: Goal name and positive target amount | E53: Goal is created with zero/current progress. | F53: Not Executed | G53: Not Executed
B54: GOL2 | C54: Contribute to goal | D54: Positive contribution to owned goal | E54: Saved amount and progress percentage increase correctly. | F54: Not Executed | G54: Not Executed
B55: GOL3 | C55: Complete savings goal | D55: Contribution reaches target | E55: Goal status becomes completed and reaches 100%. | F55: Not Executed | G55: Not Executed
B56: GOL4 | C56: Goal milestone notifications | D56: Contributions cross configured milestones | E56: Each milestone produces the expected notification once. | F56: Not Executed | G56: Not Executed
B57: GOL5 | C57: Edit own goal | D57: Update owned goal name/target | E57: Goal updates and progress is recalculated. | F57: Not Executed | G57: Not Executed
B58: GOL6 | C58: Prevent cross-user goal access | D58: Read/update/contribute/delete another user's goal | E58: Operations return not found/denied. | F58: Not Executed | G58: Not Executed
B59: GOL7 | C59: Delete own goal | D59: Delete an owned goal | E59: Goal is removed successfully. | F59: Not Executed | G59: Not Executed
A60: Analytics | B60: ANA1 | C60: Monthly financial summary | D60: Month with income and expenses | E60: Income, expenses, net balance, and savings rate are correct. | F60: Not Executed | G60: Not Executed
B61: ANA2 | C61: Spending by category | D61: Expenses across several categories | E61: Category totals and chart values match recorded expenses. | F61: Not Executed | G61: Not Executed
B62: ANA3 | C62: Income versus expenses | D62: Month with both transaction types | E62: Comparison chart uses accurate totals. | F62: Not Executed | G62: Not Executed
B63: ANA4 | C63: Six-month cash-flow trend | D63: Transactions across six months | E63: Monthly income and expense trend is chronologically correct. | F63: Not Executed | G63: Not Executed
B64: ANA5 | C64: Highest spending category | D64: Multiple expense categories | E64: Top-category insight identifies the largest total. | F64: Not Executed | G64: Not Executed
B65: ANA6 | C65: Savings analysis | D65: Income and expense data | E65: Savings rate and insight text reflect the calculated cash flow. | F65: Not Executed | G65: Not Executed
B66: ANA7 | C66: Goal analysis | D66: Active and completed goals | E66: Analytics shows accurate goal progress. | F66: Not Executed | G66: Not Executed
B67: ANA8 | C67: Analytics empty state | D67: User with no financial data | E67: Charts and totals show safe zero/empty states without crashing. | F67: Not Executed | G67: Not Executed
B68: ANA9 | C68: Premium custom date range | D68: Premium User selects valid From/To dates | E68: Selected-range totals and categories update correctly. | F68: Not Executed | G68: Not Executed
B69: ANA10 | C69: Premium 12-month trend | D69: Premium User with yearly records | E69: Twelve-month income and expense trend is displayed. | F69: Not Executed | G69: Not Executed
B70: ANA11 | C70: Reject invalid analytics range | D70: From date after To date or range over two years | E70: API returns validation error and UI shows a useful message. | F70: Not Executed | G70: Not Executed
B71: ANA12 | C71: Free User premium analytics restriction | D71: Free User calls /premium/insights | E71: API returns 403 and premium-only analysis is not displayed. | F71: Not Executed | G71: Not Executed
B72: ANA13 | C72: Admin premium analytics access | D72: Admin opens Analytics | E72: Admin can use detailed analytics for only the Admin's personal data. | F72: Not Executed | G72: Not Executed
B73: ANA14 | C73: Legacy advanced URL | D73: Open /advanced-analytics | E73: User is redirected to the unified /analytics page. | F73: Not Executed | G73: Not Executed
A74: Reports & Export | B74: RPT1 | C74: Monthly statement | D74: Select month/year | E74: Opening balance, credits, debits, closing balance, and transactions are correct. | F74: Not Executed | G74: Not Executed
B75: RPT2 | C75: PDF export | D75: Premium User exports selected period | E75: A valid PDF statement downloads with the correct period and personal data. | F75: Not Executed | G75: Not Executed
B76: RPT3 | C76: Excel export | D76: Premium User exports selected period | E76: A valid XLSX statement downloads with summary and transaction sheets. | F76: Not Executed | G76: Not Executed
B77: RPT4 | C77: Free User export restriction | D77: Free User requests PDF/XLSX export | E77: API returns 403 because Premium access is required. | F77: Not Executed | G77: Not Executed
B78: RPT5 | C78: Admin personal report | D78: Admin exports report | E78: Report contains only the Admin's own financial records. | F78: Not Executed | G78: Not Executed
A79: Notifications | B79: NOT1 | C79: List notifications | D79: Authenticated user with notifications | E79: Only that user's notifications are listed newest first. | F79: Not Executed | G79: Not Executed
B80: NOT2 | C80: Mark notification read | D80: Click an unread owned notification | E80: Notification becomes read and unread count decreases. | F80: Not Executed | G80: Not Executed
B81: NOT3 | C81: Prevent cross-user notification access | D81: Use another user's notification ID | E81: Operation returns not found/denied. | F81: Not Executed | G81: Not Executed
B82: NOT4 | C82: Monthly report notification | D82: Generate monthly report notification | E82: Notification is created once with correct type/message. | F82: Not Executed | G82: Not Executed
B83: NOT5 | C83: Notification filters | D83: Choose All, Unread, or New | E83: Only notifications matching the selected filter are displayed. | F83: Not Executed | G83: Not Executed
A84: Profile & Settings | B84: PRO1 | C84: Load profile | D84: Authenticated user | E84: Correct personal profile details are displayed. | F84: Not Executed | G84: Not Executed
B85: PRO2 | C85: Update profile | D85: Valid changed full name/profile fields | E85: Changes persist and success feedback is shown. | F85: Not Executed | G85: Not Executed
B86: PRO3 | C86: Theme preference | D86: Select light, dark, or system | E86: Theme applies immediately and persists on reload. | F86: Not Executed | G86: Not Executed
B87: PRO4 | C87: Display preferences | D87: Change currency/compact/balance settings | E87: Preferences save locally and remain after refresh. | F87: Not Executed | G87: Not Executed
B88: PRO5 | C88: Notification preferences | D88: Toggle update, summary, and budget alerts | E88: Selections persist without changing another account's server data. | F88: Not Executed | G88: Not Executed
A89: Premium Membership | B89: PRE1 | C89: View current membership | D89: Free or Premium authenticated user | E89: Correct plan, premium flag, and subscription details are returned. | F89: Not Executed | G89: Not Executed
B90: PRE2 | C90: Successful verified upgrade | D90: Valid captured payment and signature | E90: Subscription activates and role/plan reflect Premium access. | F90: Not Executed | G90: Not Executed
B91: PRE3 | C91: Reject invalid payment signature | D91: Incorrect payment signature | E91: Upgrade fails and Premium access remains locked. | F91: Not Executed | G91: Not Executed
B92: PRE4 | C92: Cancel Premium membership | D92: Premium User cancels active plan | E92: Subscription is cancelled and Premium-only APIs become inaccessible. | F92: Not Executed | G92: Not Executed
B93: PRE5 | C93: Admin role survives membership changes | D93: Admin activates/cancels membership | E93: Role remains Admin and admin permissions are preserved. | F93: Not Executed | G93: Not Executed
A94: Admin & Role Access | B94: ADM1 | C94: Admin sidebar | D94: Authenticated Admin | E94: User features, Admin entry, and Admin badge are visible. | F94: Not Executed | G94: Not Executed
B95: ADM2 | C95: Free User sidebar | D95: Authenticated Free User | E95: Normal navigation is visible and no Admin entry/badge appears. | F95: Not Executed | G95: Not Executed
B96: ADM3 | C96: Premium User sidebar | D96: Authenticated Premium User | E96: Normal navigation and Premium badge are visible; no Admin entry appears. | F96: Not Executed | G96: Not Executed
B97: ADM4 | C97: Admin dashboard | D97: Admin opens /admin | E97: System-wide account and platform summaries load successfully. | F97: Not Executed | G97: Not Executed
B98: ADM5 | C98: User management list | D98: Admin opens user management | E98: Users, roles, plans, and statuses are displayed. | F98: Not Executed | G98: Not Executed
B99: ADM6 | C99: Deactivate user | D99: Admin sets another user inactive | E99: Target account is deactivated and can no longer access protected features. | F99: Not Executed | G99: Not Executed
B100: ADM7 | C100: Change user role | D100: Admin changes user/admin role | E100: Role change persists and new authorization rules apply. | F100: Not Executed | G100: Not Executed
...

Sheet Test Summary
A1: BudgetBuddy Test Summary
A2: Module | B2: Number of Cases | C2: Executed | D2: Pass Rate
A3: Registration & Verification | B3: 8 | C3: =COUNTIFS('BudgetBuddy Test Cases'!B:B,"REG*",'BudgetBuddy Test Cases'!G:G,"<>Not Executed") | D3: =IF(C3=0,"Not Executed",COUNTIFS('BudgetBuddy Test Cases'!B:B,"REG*",'BudgetBuddy Test Cases'!G:G,"Pass")/C3)
A4: Login & Session | B4: 10 | C4: =COUNTIFS('BudgetBuddy Test Cases'!B:B,"LOG*",'BudgetBuddy Test Cases'!G:G,"<>Not Executed") | D4: =IF(C4=0,"Not Executed",COUNTIFS('BudgetBuddy Test Cases'!B:B,"LOG*",'BudgetBuddy Test Cases'!G:G,"Pass")/C4)
A5: Overview | B5: 6 | C5: =COUNTIFS('BudgetBuddy Test Cases'!B:B,"OVR*",'BudgetBuddy Test Cases'!G:G,"<>Not Executed") | D5: =IF(C5=0,"Not Executed",COUNTIFS('BudgetBuddy Test Cases'!B:B,"OVR*",'BudgetBuddy Test Cases'!G:G,"Pass")/C5)
A6: Income | B6: 6 | C6: =COUNTIFS('BudgetBuddy Test Cases'!B:B,"INC*",'BudgetBuddy Test Cases'!G:G,"<>Not Executed") | D6: =IF(C6=0,"Not Executed",COUNTIFS('BudgetBuddy Test Cases'!B:B,"INC*",'BudgetBuddy Test Cases'!G:G,"Pass")/C6)
A7: Expenses | B7: 8 | C7: =COUNTIFS('BudgetBuddy Test Cases'!B:B,"EXP*",'BudgetBuddy Test Cases'!G:G,"<>Not Executed") | D7: =IF(C7=0,"Not Executed",COUNTIFS('BudgetBuddy Test Cases'!B:B,"EXP*",'BudgetBuddy Test Cases'!G:G,"Pass")/C7)
A8: Accounts | B8: 5 | C8: =COUNTIFS('BudgetBuddy Test Cases'!B:B,"ACC*",'BudgetBuddy Test Cases'!G:G,"<>Not Executed") | D8: =IF(C8=0,"Not Executed",COUNTIFS('BudgetBuddy Test Cases'!B:B,"ACC*",'BudgetBuddy Test Cases'!G:G,"Pass")/C8)
A9: Budgets | B9: 7 | C9: =COUNTIFS('BudgetBuddy Test Cases'!B:B,"BUD*",'BudgetBuddy Test Cases'!G:G,"<>Not Executed") | D9: =IF(C9=0,"Not Executed",COUNTIFS('BudgetBuddy Test Cases'!B:B,"BUD*",'BudgetBuddy Test Cases'!G:G,"Pass")/C9)
A10: Savings Goals | B10: 7 | C10: =COUNTIFS('BudgetBuddy Test Cases'!B:B,"GOL*",'BudgetBuddy Test Cases'!G:G,"<>Not Executed") | D10: =IF(C10=0,"Not Executed",COUNTIFS('BudgetBuddy Test Cases'!B:B,"GOL*",'BudgetBuddy Test Cases'!G:G,"Pass")/C10)
A11: Analytics | B11: 14 | C11: =COUNTIFS('BudgetBuddy Test Cases'!B:B,"ANA*",'BudgetBuddy Test Cases'!G:G,"<>Not Executed") | D11: =IF(C11=0,"Not Executed",COUNTIFS('BudgetBuddy Test Cases'!B:B,"ANA*",'BudgetBuddy Test Cases'!G:G,"Pass")/C11)
A12: Reports & Export | B12: 5 | C12: =COUNTIFS('BudgetBuddy Test Cases'!B:B,"RPT*",'BudgetBuddy Test Cases'!G:G,"<>Not Executed") | D12: =IF(C12=0,"Not Executed",COUNTIFS('BudgetBuddy Test Cases'!B:B,"RPT*",'BudgetBuddy Test Cases'!G:G,"Pass")/C12)
A13: Notifications | B13: 5 | C13: =COUNTIFS('BudgetBuddy Test Cases'!B:B,"NOT*",'BudgetBuddy Test Cases'!G:G,"<>Not Executed") | D13: =IF(C13=0,"Not Executed",COUNTIFS('BudgetBuddy Test Cases'!B:B,"NOT*",'BudgetBuddy Test Cases'!G:G,"Pass")/C13)
A14: Profile & Settings | B14: 5 | C14: =COUNTIFS('BudgetBuddy Test Cases'!B:B,"PRO*",'BudgetBuddy Test Cases'!G:G,"<>Not Executed") | D14: =IF(C14=0,"Not Executed",COUNTIFS('BudgetBuddy Test Cases'!B:B,"PRO*",'BudgetBuddy Test Cases'!G:G,"Pass")/C14)
A15: Premium Membership | B15: 5 | C15: =COUNTIFS('BudgetBuddy Test Cases'!B:B,"PRE*",'BudgetBuddy Test Cases'!G:G,"<>Not Executed") | D15: =IF(C15=0,"Not Executed",COUNTIFS('BudgetBuddy Test Cases'!B:B,"PRE*",'BudgetBuddy Test Cases'!G:G,"Pass")/C15)
A16: Admin & Role Access | B16: 12 | C16: =COUNTIFS('BudgetBuddy Test Cases'!B:B,"ADM*",'BudgetBuddy Test Cases'!G:G,"<>Not Executed") | D16: =IF(C16=0,"Not Executed",COUNTIFS('BudgetBuddy Test Cases'!B:B,"ADM*",'BudgetBuddy Test Cases'!G:G,"Pass")/C16)
A17: Navigation & Compatibility | B17: 5 | C17: =COUNTIFS('BudgetBuddy Test Cases'!B:B,"NAV*",'BudgetBuddy Test Cases'!G:G,"<>Not Executed") | D17: =IF(C17=0,"Not Executed",COUNTIFS('BudgetBuddy Test Cases'!B:B,"NAV*",'BudgetBuddy Test Cases'!G:G,"Pass")/C17)
A18: TOTAL | B18: 108
